# 1. å¤šæ€çš„åº”ç”¨

1. é¢å‘çˆ¶ç±»ç¼–ç¨‹
2. é¢å‘æ¥å£ç¼–ç¨‹
   * å¯¹è±¡çš„ç¼–è¯‘æ—¶ç±»å‹å†™æˆæ¥å£,å¯¹è±¡çš„è¿è¡Œæ—¶ç±»å‹å†™æˆå®ç°ç±»
   * ***æ–¹æ³•çš„è¿”å›ç±»å‹å†™æˆæ¥å£,æ–¹æ³•çš„è¿”å›ç»“æœå†™æˆå®ç°ç±»***
   * æ–¹æ³•çš„å‚æ•°åˆ—è¡¨å†™æˆæ¥å£,å¯ä»¥ä¼ å…¥æ¥å£çš„å®ç°ç±».

# 2. ç®€å•å·¥å‚è®¾è®¡æ¨¡å¼

å¹¶ä¸å±äº23ç§è®¾è®¡æ¨¡å¼

ç›®çš„:å°†å¯¹è±¡çš„åˆ›å»ºå’Œå¯¹è±¡çš„ä½¿ç”¨è¿›è¡Œåˆ†ç¦».  å¯¹è±¡çš„åˆ›å»ºç»Ÿä¸€äº¤ç»™å·¥å‚å»å®Œæˆ.

ä¼ ç»Ÿçš„æ¨¡å¼: IUserDao userDao = new UserDaoImpl();//ä¸»åŠ¨å¯»æ‰¾,ä¸»åŠ¨åœºæ™¯.

éƒ¨åˆ†å¯¹è±¡çš„åˆ›å»ºå¯èƒ½æ­¥éª¤æ¯”è¾ƒå¤æ‚,ç”šè‡³å¯èƒ½éœ€è¦æ¶ˆè€—ä¸€å®šçš„æ—¶é—´.è®©ä½¿ç”¨è€…æ— éœ€å…³å¿ƒå¯¹è±¡åˆ›å»ºçš„è¿‡ç¨‹.

## 1. ç‰ˆæœ¬ä¸€

æ ¹æ®ä¼ å…¥çš„å‚æ•°,æ¥è¿”å›æŸä¸ªæ¥å£/ç±»çš„å…·ä½“çš„å®ä¾‹

~~~java
package tech.aistar.design.factory.v1;

/**
 * æœ¬æ¥ç”¨æ¥æ¼”ç¤º: ç®€å•å·¥å‚
 *
 * @author success
 * @date 2023/7/31 09:20:15
 */
public class SenderFactory {

    //    å®ç°æ­¥éª¤ -  æ ¹æ®ä¼ å…¥çš„å‚æ•°,æ¥è¿”å›æŸä¸ªæ¥å£/ç±»çš„å…·ä½“çš„å®ä¾‹
    //    èƒŒåçš„ç†è®º: æ–¹æ³•çš„è¿”å›ç±»å‹å†™æˆæ¥å£,æ–¹æ³•çš„è¿”å›ç»“æœå†™æˆå®ç°ç±»

    public Sender getInstance(String type){
        //å®šä¹‰ä¸€ä¸ªæ¥å£å¯¹è±¡
        Sender sender = null;

        switch (type){
            case "SMS":
                sender = new SMSSender();
                break;
            case "EMAIL":
                sender = new EmailSender();
                break;
        }
        return sender;
    }
}
~~~

`å¼Šç«¯ - 1. è¿˜éœ€è¦å»åˆ›å»ºå·¥å‚å¯¹è±¡  2. å‚æ•°ä¸å¯æ§çš„,å¯èƒ½ä¼šä¼ å…¥ä¸€ä¸ªéå‚æ•°-å¯¼è‡´å·¥å‚åœºæ™¯å¯¹è±¡å¤±è´¥!`



## 2.  ç‰ˆæœ¬äºŒ - ç¬”è¯•æ¨è

> æ€»ç»“:
>
> ä¼˜ç‚¹ - ç®€å•/ç»“æ„
>
> ç¼ºç‚¹ - æ¯æ¬¡å¦‚æœæ–°å¢ä¸€ä¸ªäº§å“,é‚£ä¹ˆå¯¹äºå·¥å‚ç±»æ¥è¯´ - è¶Šæ— èƒ½ä¸ºåŠ› -  **å·¥å‚ç±»ä¼šè¿èƒŒå¼€é—­åŸåˆ™.**
>
> ***æ–°å¢äº§å“ - éœ€è¦ä¿®æ”¹å·¥å‚ç±»***

> ~~~java
> package tech.aistar.design.factory.v2;
> 
> import tech.aistar.design.factory.v1.EmailSender;
> import tech.aistar.design.factory.v1.SMSSender;
> import tech.aistar.design.factory.v1.Sender;
> 
> /**
>  * æœ¬æ¥ç”¨æ¥æ¼”ç¤º: ç®€å•å·¥å‚
>  *
>  * @author success
>  * @date 2023/7/31 09:20:15
>  */
> @SuppressWarnings("all")
> public class SenderFactory {
>     //ç±»å‹æ˜¯å®‰å…¨çš„
>     public static final String SMS = "SMS";
>     public static final String EMAIL = "EMAIL";
>     
>     public static Sender getInstance(String type){
>         //å®šä¹‰ä¸€ä¸ªæ¥å£å¯¹è±¡
>         Sender sender = null;
> 
>         switch (type){
>             case SMS:
>                 sender = new SMSSender();
>                 break;
>             case EMAIL:
>                 sender = new EmailSender();
>                 break;
>         }
>         return sender;
>     }
> }
> ~~~

## 3. å¤šæ–¹æ³•å·¥å‚

~~~java
package tech.aistar.design.factory.v3;

import tech.aistar.design.factory.v1.EmailSender;
import tech.aistar.design.factory.v1.SMSSender;
import tech.aistar.design.factory.v1.Sender;

/**
 * æœ¬æ¥ç”¨æ¥æ¼”ç¤º: ç®€å•å·¥å‚è®¾è®¡æ¨¡å¼ - å¤šæ–¹æ³•å·¥å‚
 *
 * ä¸€ä¸ªæ–¹æ³•è´Ÿè´£åˆ›å»ºå…·ä½“çš„å®ä¾‹
 *
 * @author success
 * @date 2023/7/31 09:53:35
 */
public class SenderFactory {

    public Sender createSMS(){
        return new SMSSender();
    }

    public Sender createEmail(){
        return new EmailSender();
    }
}
~~~



## 4. å¤šé™æ€æ–¹æ³•å·¥å‚

~~~java
public class SenderFactory {

    public static Sender createSMS(){
        return new SMSSender();
    }

    public static Sender createEmail(){
        return new EmailSender();
    }
}
~~~



# 3. å·¥å‚æ–¹æ³•è®¾è®¡æ¨¡å¼

çœŸæ­£å±äº23ç§GOF

ç›®çš„ - ä¸€ä¸ªå·¥å‚åªè´Ÿè´£åˆ›å»ºä¸€ä¸ªäº§å“ - è®¾è®¡çš„ç›®çš„æ˜¯ä¸ºäº†è®©å·¥å‚ç±»ç¬¦åˆå¼€é—­åŸåˆ™.

ç¼ºç‚¹: å¯¼è‡´é¡¹ç›®ä¸­äº§ç”Ÿå¤§é‡çš„å·¥å‚ç±» - ç»´æŠ¤å¤§é‡çš„å·¥å‚ç±».

ä¼˜ç‚¹: å‡è½»å•ä¸ªå·¥å‚çš„å‹åŠ›,ä½¿å¾—å·¥å‚ç±»ç¬¦åˆå¼€é—­åŸåˆ™



# 4. æŠ½è±¡å·¥å‚è®¾è®¡æ¨¡å¼

1. å®¢æˆ·ç«¯(ä½¿ç”¨è€…)å¹¶ä¸çŸ¥é“å…·ä½“æœ‰å¤šå°‘ä¸ªäº§å“è¢«è®¾è®¡å‡ºæ¥äº†.
2. æŠŠåŒä¸€ä¸ªäº§å“æ—çš„äº§å“è®¾è®¡åœ¨ä¸€èµ·,ä¿è¯å®¢æˆ·ç«¯ä½¿ç”¨çš„å°±æ˜¯åŒä¸€ä¸ªäº§å“æ—ä¸­çš„äº§å“.
3. æŠ½è±¡å·¥å‚ä¹Ÿæ˜¯ç¬¦åˆå¼€é—­åŸåˆ™.

---



# 5. å‡½æ•°å¼æ¥å£

å‡½æ•°å¼æ¥å£(ä½¿ç”¨@FunctionalInterfaceä¿®é¥°) - è¿™ä¸ªæ¥å£åªèƒ½æœ‰ä¸€ä¸ªæŠ½è±¡æ–¹æ³•.

ä¸€æ—¦æ˜¯å‡½æ•°å¼æ¥å£,å¯ä»¥é‡‡ç”¨lambdaè¡¨è¾¾å¼[jdk8.0æ–°ç‰¹æ€§]æ¥æ›¿ä»£åŒ¿åå†…éƒ¨ç±»çš„å†™æ³•



# 6. java.lang.Object

> Objectæ˜¯æ‰€æœ‰ç±»çš„æ ¹ç±»,çˆ¶ç±»,åŸºç±».ä¸€ä¸ªç±»å¦‚æœæ˜ç¡®æŒ‡å®šå®ƒçš„çˆ¶ç±»,é‚£ä¹ˆé»˜è®¤å°±æ˜¯ç»§æ‰¿Object
>
> æ¥å£å¹¶ä¸ç»§æ‰¿Object

----

1. Class<?> getClass();//è·å–è¿è¡Œæ—¶ç±»å‹ - å­¦ä¹ åå°„æŠ€æœ¯(å­¦ä¹ æ¡†æ¶çš„åŸºç¡€) - java.lang.Class<T>å­¦ä¹ åå°„æŠ€æœ¯åŸºç¡€çš„ç±».

2. String toString();//é»˜è®¤æ‰“å°çš„æ˜¯å¯¹è±¡çš„å†…å­˜åœ°å€,ä¸€èˆ¬æ˜¯éœ€è¦é‡å†™æ¥æ»¡è¶³å®é™…çš„æ‰“å°éœ€æ±‚.

3. **public boolean equals(Object obj);//åŸºæœ¬ç±»å‹æ¯”è¾ƒä½¿ç”¨==,å¯¹è±¡ç±»å‹æ¯”è¾ƒä½¿ç”¨equals.**

   ~~~java
   Object:
   public boolean equals(Object obj) {
     return (this == obj);
   }
   ~~~

4. **public native int hashCode();**

5. **protected native Object clone() throws CloneNotSupportedException;//å…‹éš†æ–¹æ³•**

6. notify()å’ŒnotifyAll(),wait()

## 1. equalsæ–¹æ³•

é‡å†™æ­¥éª¤

1. éç©ºæ€§
2. è‡ªåæ€§
3. ç±»å‹ä¸€è‡´æ€§
4. å®šåˆ¶æ¯”è¾ƒçš„è§„åˆ™

---

## 2. hashCodeæ–¹æ³•

> è¯¥æ–¹æ³•æ˜¯å¯ä»¥ä¸æä¾›çš„,å¹¶ä¸å½±å“equalsæ¯”è¾ƒçš„ç»“æœ,ä½†æ˜¯æä¾›ä¹‹å,**å¯ä»¥æœ‰æ•ˆæé«˜æ•ˆç‡.**
>
> èµ·å§‹è´¨æ•°æ˜¯31 - å‡å°‘å“ˆå¸Œå†²çª/ç¢°æ’.
>
> å“ˆå¸Œæ¡¶,æ¡¶æ•°ç»„,å“ˆå¸Œç®—æ³•,å“ˆå¸Œç¢°æ’/å“ˆå¸Œå†²çª.
>
> 1. æ¡¶æ•°ç»„ - æ ¹æ®å“ˆå¸Œç®—æ³•å¾—åˆ°ä¸€ä¸ªå“ˆå¸Œå€¼,æ ¹æ®å“ˆå¸Œå€¼å°±å¯ä»¥å¾—åˆ°ä¸€ä¸ªåœ°å€/ä¸‹æ ‡
> 2. å“ˆå¸Œå†²çª - ä¿©æ¬¡å¾—åˆ°çš„å“ˆå¸Œå€¼æ˜¯ä¸€æ ·çš„.

---

1. ä¸åŒå¯¹è±¡çš„hashå€¼å¯èƒ½æ˜¯ä¸€æ · - å“ˆå¸Œå†²çª/ç¢°æ’
2. equalsè¿”å›trueçš„ä¿©ä¸ªå¯¹è±¡,ä¸€å®šæ˜¯åŒä¸€ä¸ªå¯¹è±¡.

---

## 3. é¢è¯•==å’ŒequalsåŒºåˆ«

1. == 

   **åŸºæœ¬ç±»å‹ä½¿ç”¨**==æ¯”è¾ƒå€¼,å¯¹è±¡ç±»å‹ä½¿ç”¨==æ¯”è¾ƒçš„æ˜¯åœ°å€.

2. equals

â€‹		**å¯¹è±¡ç±»å‹**é‡‡ç”¨equalsè¿›è¡Œæ¯”è¾ƒ,é»˜è®¤ä½¿ç”¨çš„æ˜¯Objectä¸­çš„(==),ä¸€èˆ¬éœ€è¦é‡å†™equals

---

## 4. cloneæ–¹æ³•

> ä¼˜åŠ¿ - æ¯”è‡ªå·±newæ€§èƒ½é«˜,å› ä¸ºå®ƒä¸èµ°æ„é€ æ–¹æ³•,ç›´æ¥åœ¨å†…å­˜ä¸­è¿›è¡Œå¤åˆ¶

1. æµ…å±‚å…‹éš† - æµ…æ‹·è´ - æµ…å¤åˆ¶

ä½¿ç”¨Objectä¸­çš„clone - æµ…æ‹·è´ ,ç”±äºObjectä¸­çš„cloneæ–¹æ³•ä½¿ç”¨protectedä¿®é¥°çš„.å› æ­¤éœ€è¦é‡å†™cloneæ–¹æ³•,ä¿®æ”¹æˆpublic.

ç‰¹ç‚¹:

1. å¯¹äºåŸºæœ¬æ•°æ®ç±»å‹ä»¥åŠStringæˆ–è€…Date,å¤åˆ¶çš„å°±æ˜¯å€¼
2. å¯¹äºå¼•ç”¨ç±»å‹,å¤åˆ¶çš„åœ°å€.

```java
//1. ä¿®æ”¹åŸå¯¹è±¡çš„åŸºæœ¬æ•°æ®ç±»å‹,String,Dateç±»å‹éƒ½ä¸ä¼šå¯¹å‰¯æœ¬å¯¹è±¡äº§ç”Ÿå½±å“
//2. ä¿®æ”¹å¯¹è±¡ç±»å‹,ä¼šå¯¹å‰¯æœ¬å¯¹è±¡é€ æˆå½±å“
```

2. æ·±å±‚å…‹éš† - æ·±æ‹·è´ - æ·±å¤åˆ¶

å°†åŸå‹å¯¹è±¡çš„æ— è®ºæ˜¯åŸºæœ¬æ•°æ®ç±»å‹è¿˜æ˜¯å¼•ç”¨æ•°æ®ç±»å‹å…¨éƒ¨æ‹·è´ä¸€ä»½ç»™å‰¯æœ¬.ä¿®æ”¹åŸå‹å¯¹è±¡,éƒ½ä¸ä¼šå¯¹å‰¯æœ¬å¯¹è±¡é€ æˆå½±å“.

~~~java
éœ€è¦æ‰‹å†™cloneæ–¹æ³•,ç„¶åå°†åŸå‹å¯¹è±¡ä¸­çš„æ¯ä¸ªå±æ€§å€¼,éƒ½è¦æ‰‹åŠ¨ä¸€ä¸€èµ‹å€¼åˆ°æ–°newå‡ºæ¥çš„å¯¹è±¡.
~~~

## 6. åŸå‹æ¨¡å¼

ä¸€ä¸ªå¯¹è±¡çš„äº§ç”Ÿå¯ä»¥ä¸ç”±é›¶èµ·æ­¥ï¼Œç›´æ¥ä»ä¸€ä¸ªå·²ç»å…·å¤‡ä¸€å®šé›å½¢çš„å¯¹è±¡å…‹éš†ï¼Œç„¶åå†ä¿®æ”¹ä¸ºç”Ÿäº§éœ€è¦çš„å¯¹è±¡ã€‚

ç”¨ä¸€ä¸ªå·²ç»åˆ›å»ºçš„å®ä¾‹ä½œä¸ºåŸå‹,é€šè¿‡å¤åˆ¶è¯¥åŸå‹å¯¹è±¡æ¥åˆ›å»ºä¸€ä¸ªå’ŒåŸå‹å¯¹è±¡ç›¸åŒçš„æ–°å¯¹è±¡

ä½¿ç”¨åœºæ™¯:

1. å¯¹è±¡çš„åˆ›å»ºéå¸¸å¤æ‚,å¯ä»¥ä½¿ç”¨åŸå‹æ¨¡å¼æ¥å¿«é€Ÿåˆ›å»ºå¯¹è±¡
2. æ€§èƒ½å’Œå®‰å…¨è¦æ±‚å¾—åˆ°æé«˜.

---

> ~~~java
> Email email = new Email();
> email.setFrom("å‘é€è€…é‚®ç®±");
> email.setTitle("é‚®ç®±çš„æ ‡é¢˜");
> email.setText("é‚®ç®±çš„æ­£æ–‡");
> 
> for(int i=0;i<10;i++){
>   Email copy = (Email)email.clone();
>   //é‚®ç®±åªæ˜¯æ”¶ä»¶åœ°å€ä¸ä¸€æ ·æ»´!
>   copy.setTo("aistar"+i+"@it.com");
>   mailSender.send(copy);
> }
> ~~~

---

## 7. finalize() 

> protected void finalize() throws Throwable { },è¿‡æ—¶çš„æ–¹æ³•
>
> ä¸€èˆ¬ä¸ä¼šè‡ªå·±è°ƒç”¨çš„.  
>
> 1. GCåªèƒ½å›æ”¶newå‡ºæ¥çš„å¯¹è±¡.
> 2. å½“GCå›æ”¶ä¸€ä¸ªåƒåœ¾å¯¹è±¡ä¹‹å‰,ä¼šå…ˆè°ƒç”¨è¿™ä¸ªå¯¹è±¡çš„finalize() , è¿›è¡Œèµ„æº,ç©ºé—´,å†…å­˜ç­‰ç­‰ä¸€äº›é‡Šæ”¾çš„åŠ¨ä½œ.

---

ç¬”è¯•é¢˜:   finalå’Œfinallyä»¥åŠfinalizeä¸‰è€…ä¹‹é—´çš„åŒºåˆ«.

---



# 7. IntegeråŒ…è£…ç±»å‹ğŸ’¯

> **int=>Integer**,byte=>Byte,short=>Short,long=>Long,float=>Float,double=>Double,boolean=>Boolean,**char=>Character**

1. api: java.lang
2. æ˜¯intç±»å‹çš„åŒ…è£…ç±»å‹,æœ¬èº«å±äºå¯¹è±¡ç±»å‹.  å¯ä»¥æŠŠåŸºæœ¬æ•°æ®ç±»å‹ä½œä¸ºå¯¹è±¡æ¥æ“ä½œ.
3. æŠ½è±¡çš„çˆ¶ç±»java.lang.Number - ç›´æ¥çš„å­ç±»Byte,Short,Integer,Long,Float,Double

## 1. æ„é€ æ–¹æ³•

1. Integer(int value);//åˆ©ç”¨åŸºæœ¬æ•°æ®ç±»å‹æ„å»ºIntegerç±»å‹,åŸºæœ¬æ•°æ®ç±»å‹int=>åŒ…è£…ç±»å‹Integer
2. Integer(String s);//å­—ç¬¦ä¸²å¿…é¡»æ•°å­—å½¢å¼çš„å­—ç¬¦ä¸²,Stringç±»å‹è½¬æˆIntegerç±»å‹,å¦‚æœä¼ å…¥çš„æ˜¯ä¸€ä¸ªéæ³•çš„å­—ç¬¦ä¸²,æŠ›å‡ºjava.lang.NumberFormatExceptionå¼‚å¸¸ - æ•°å­—æ ¼å¼åŒ–å¤±è´¥çš„å¼‚å¸¸.

## 2. å¸¸ç”¨æ–¹æ³•

1. int intValue();//Intergetç±»å‹è½¬æ¢æˆintç±»å‹
2. static Integer valueOf(int n);//å°†åŸºæœ¬ç±»å‹è½¬æ¢æˆIntegerç±»å‹
2. static Integer valueOf(String n);//String=>Integer
2. static int parseInt(String s);//å°†æ•°å­—å½¢å¼çš„å­—ç¬¦ä¸²è½¬æ¢æˆint,å¦‚æœå­—ç¬¦ä¸²æ˜¯éæ³•çš„,æŠ›å‡ºjava.lang.NumberFormatException
2. String toString();//å°†Integer=>String
2. è¿›åˆ¶ç›¸å…³çš„æ–¹æ³•
2. å¸¸é‡

## 3. å‰–ævalueOfæ–¹æ³•çš„åº•å±‚

> ç»“è®º:
>
> ~~~java
> //ç»“è®º: åªè¦å€¼åœ¨[-128,127]ä¹‹é—´,ä½¿ç”¨==æ¯”è¾ƒçš„ç»“æœå°±æ˜¯true.
> Integer v1 = Integer.valueOf(-128);
> Integer v2 = Integer.valueOf(-128);
> System.out.println(v1 == v2);
> ~~~
>
> æºç :
>
> ~~~java
> public static Integer valueOf(int i) {
>   if (i >= IntegerCache.low && i <= IntegerCache.high)
>     return IntegerCache.cache[i + (-IntegerCache.low)];
>   return new Integer(i);
> }
> 
> //Integerå†…éƒ¨çš„ç¼“å­˜æœºåˆ¶
> //é™æ€å†…éƒ¨ç±»
> private static class IntegerCache {
>     static final int low = -128;
>   
>     static final int high;
>     
>     //ç¼“å­˜æ•°ç»„
>     static final Integer[] cache;
>   
>     static{
>        int h = 127;
>       
>        ...
>        //ç¼“å­˜æ•°ç»„çš„å¤§å°
>        int size = (high - low) + 1;
>          
>        high = h;
>       
>       //å¯¹ç¼“å­˜æ•°ç»„è¿›è¡Œåˆå§‹åŒ–
>       if (archivedCache == null || size > archivedCache.length) {
>         Integer[] c = new Integer[size];//å­˜æ”¾äº†256ä¸ªæ•°æ®
>         
>         int j = low;//low=-128
>         for(int i = 0; i < c.length; i++) {
>           //cæ•°ç»„å­˜å‚¨äº†[-128,127]ä¹‹é—´çš„æ•°æ®
>           c[i] = new Integer(j++);
>         }
>         archivedCache = c;
>       }
>       cache = archivedCache;
>     }
>  }
> ~~~

## 4. æŸ¥çœ‹jvmæŒ‡ä»¤

> ~~~java
> public class IntegerDemo{
>    public static void main(String[] args){
>        Integer m1 = 128;
>        Integer m2 = 128;
>        System.out.println(m1 == m2);
>    }
> }
> ~~~

> javac IntegerDemo.java
>
> javap -c IntegerDemo
>
> ~~~java
> admindeMacBook-Pro:Desktop admin$ javap -c IntegerDemo
> Compiled from "IntegerDemo.java"
> public class IntegerDemo {
>   public IntegerDemo();
>     Code:
>        0: aload_0
>        1: invokespecial #1                  // Method java/lang/Object."<init>":()V
>        4: return
> 
>   public static void main(java.lang.String[]);
>     Code:
>        0: sipush        128
>        3: invokestatic  #7                  // Method java/lang/Integer.valueOf:(I)Ljava/lang/Integer;
>        6: astore_1
>        7: sipush        128
>       10: invokestatic  #7                  // Method java/lang/Integer.valueOf:(I)Ljava/lang/Integer;
>       13: astore_2
>       14: getstatic     #13                 // Field java/lang/System.out:Ljava/io/PrintStream;
>       17: aload_1
>       18: aload_2
>       19: if_acmpne     26
>       22: iconst_1
>       23: goto          27
>       26: iconst_0
>       27: invokevirtual #19                 // Method java/io/PrintStream.println:(Z)V
>       30: return
> }
> ~~~



## 5. ç¬”è¯•-Integerå’Œintçš„åŒºåˆ«

> 1.Integeræ˜¯intçš„åŒ…è£…ç±»ï¼Œintåˆ™æ˜¯javaçš„ä¸€ç§åŸºæœ¬çš„æ•°æ®ç±»å‹ï¼›
>
> 2.Integerå˜é‡å¿…é¡»å®ä¾‹åŒ–ä¹‹åæ‰èƒ½ä½¿ç”¨ï¼Œè€Œintå˜é‡ä¸éœ€è¦å®ä¾‹åŒ–ï¼›
>
> 3.Integerå®é™…æ˜¯å¯¹è±¡çš„å¼•ç”¨ï¼Œå½“newä¸€ä¸ªIntegeræ—¶ï¼Œå®é™…ä¸Šç”Ÿæˆä¸€ä¸ªæŒ‡é’ˆæŒ‡å‘å¯¹è±¡ï¼Œè€Œintåˆ™ç›´æ¥å­˜å‚¨æ•°å€¼
>
> 4.Integerçš„é»˜è®¤å€¼æ˜¯nullï¼Œè€Œintçš„é»˜è®¤å€¼æ˜¯0ã€‚

---
